gnucash_asx_fetch.py
gnucash_asx_fetch-1.8.dist-info/METADATA
gnucash_asx_fetch-1.8.dist-info/WHEEL
gnucash_asx_fetch-1.8.dist-info/entry_points.txt
gnucash_asx_fetch-1.8.dist-info/top_level.txt
gnucash_asx_fetch-1.8.dist-info/RECORD
