Metadata-Version: 2.4
Name: gnucash-asx-fetch
Version: 1.8
Summary: Utility to fetch and add current ASX prices to one or more gnucash XML files
Author-email: Mark Blakeney <mark.blakeney@bullet-systems.net>
License-Expression: GPL-3.0-or-later
Project-URL: Homepage, https://github.com/bulletmark/gnucash-asx-fetch
Keywords: gnucash,finance-quote
Classifier: Programming Language :: Python :: 3
Requires-Python: >=3.7
Requires-Dist: yfinance
